{
    "doi": "10.5281/zenodo.7460141",
    "title": "World Flora Online Plant List *VERSION*",
    "alias": "WFO Plant List *VERSION*",
    "description": "The consensus taxonomy of plants used as the backbone for the World Flora Online (WFO, https://www.worldfloraonline.org/) portal, and issued as editions of the WFO Plant List (https://wfoplantlist.org). New versions of this checklist are released every six months in June and December: this is release *VERSION*. The history of data development for the WFO taxonomic backbone is given on the WFO Plant List background page (https://wfoplantlist.org/background). Taxonomic names are incorporated into WFO from nomenclators International Plant Name Index (IPNI, https://www.ipni.org/) for vascular plants, and Tropicos (https://www.tropicos.org/home) for bryophytes. Taxonomic and nomenclatural updates are incorporated from the WFO's Taxonomic Expert Networks (TENs, https://about.worldfloraonline.org/tens) and the World Checklist of Vascular Plants (WCVP, https://powo.science.kew.org/about-wcvp), facilitated by the Royal Botanic Gardens, Kew.",
    "issued": "2023-06-21",
    "version": "2023-06",
    "contact": {
        "orcid": "0000-0002-8677-5688",
        "given": "Alan",
        "family": "Elliott",
        "email": "taxwg@worldfloraonline.org"
    },
    "creator": [
        {
            "email": "taxwg@worldfloraonline.org",
            "url": "http://www.worldfloraonline.org",
            "organisation": "World Flora Online"
        }
    ],
    "editor": [
        {
            "orcid": "0000-0002-1640-9156",
            "given": "Example",
            "family": "Example",
            "note": "Curator of some example ."
        }
    ],
    "publisher": {
        "email": "taxwg@worldfloraonline.org",
        "url": "http://www.worldfloraonline.org",
        "organisation": "World Flora Online"
    },
    "contributor": [
        {
            "orcid": "0009-0009-8267-890X",
            "given": "Emma",
            "family": "Wrankmore",
            "organisation": "IPNI (International Plant Names Index)"
        },
        {
            "orcid": "0009-0005-9205-1351",
            "given": "Helen",
            "family": "Hartley",
            "organisation": "IPNI (International Plant Names Index)"
        },
        {
            "orcid": "0000-0002-6507-8293",
            "given": "Jonathan",
            "family": "Krieger",
            "organisation": "IPNI (International Plant Names Index)"
        },
        {
            "orcid": "0000-0002-2205-0610",
            "given": "Kanchi",
            "family": "Gandhi",
            "organisation": "IPNI (International Plant Names Index)"
        }
    ],
    "keyword": [
        "Global Strategy for Plant Conservation",
        "Plants",
        "Bryophytes",
        "Taxonomic backbone"
    ],
    "geographicScope": "global",
    "taxonomicScope": "Plantae, Bryophyta, Marchantiophyta, Anthocerotophyta,",
    "temporalScope": "Consensus taxonomy as of 2023-06-21",
    "confidence": 5,
    "completeness": 95,
    "license": "cc0",
    "url": "https://wfoplantlist.org",
    "logo": "https://list.worldfloraonline.org/rhakhis/ui/logo1024.png",
    "label": "World Flora Online Plant List *VERSION* (*VERSION*)",
    "citation": "<div class=\"csl-entry\">World Flora Online. (*YEAR*). <span style=\"font-style: italic\">World Flora Online Plant List *VERSION*</span> (G. Anderson, G. c. Andrella, M. Anguiano, W. h. Ardi, H. Atkins, J. j. Atwood, X. Aubriot, W. Baker, A. p. Balan, F. Bartolucci, L. Bohs, M. Bonifacino, L. Borges, J. c. Brinda, A. Bruneau, C. s. d. Carvalho, F. Chiarini, T. Couvreur, D. Crowley, et al., Eds.; Version *VERSION*). World Flora Online. https://doi.org/10.5281/zenodo.7460141</div>",
    "private": false
}